{"bugs":[{"cf_status_firefox_esr31":"---","cf_status_b2g_2_1_s":"---","blocks":[325861,344905,778810],"is_cc_accessible":true,"cf_tracking_b2g":"---","cf_status_firefox16":"wontfix","keywords":["crash","csectype-uaf","regression","sec-critical","testcase","testcase-wanted"],"cf_qa_whiteboard":"","cf_status_firefox17":"fixed","url":"","qa_contact":"","cf_status_firefox38":"---","cf_tracking_esr10":"17+","cf_fx_iteration":"---","cf_tracking_firefox_relnote":"---","cf_last_resolved":"2012-10-21T12:38:53Z","cf_fx_points":"---","cc_detail":[{"email":"21@vingtetun.org","real_name":"Vivien Nicolas (:vingtetun) (:21) - (NOT reading bugmails, needinfo? please)","name":"21@vingtetun.org","id":282474},{"email":"abillings@mozilla.com","real_name":"Al Billings [:abillings]","name":"abillings@mozilla.com","id":280903},{"email":"akeybl@mozilla.com","real_name":"Alex Keybl [:akeybl]","name":"akeybl@mozilla.com","id":425645},{"email":"anthony.s.hughes@gmail.com","real_name":"Anthony Hughes, QA Mentor (:ashughes)","name":"anthony.s.hughes@gmail.com","id":279076},{"email":"bugs@pettay.fi","real_name":"Olli Pettay [:smaug]","name":"bugs@pettay.fi","id":39966},{"email":"bzbarsky@mit.edu","real_name":"Not doing reviews right now","name":"bzbarsky@mit.edu","id":20209},{"email":"kairo@kairo.at","real_name":"Robert Kaiser (:kairo@mozilla.com)","name":"kairo@kairo.at","id":5189},{"email":"mark@wolfbeast.com","real_name":"Mark Straver","name":"mark@wolfbeast.com","id":364942},{"email":"mats@mozilla.com","real_name":"Mats Palmgren (:mats)","name":"mats@mozilla.com","id":5168},{"email":"roc@ocallahan.org","real_name":"Robert O'Callahan (:roc) (Mozilla Corporation)","name":"roc@ocallahan.org","id":5038},{"email":"scoobidiver@netcourrier.com","real_name":"Scoobidiver (away)","name":"scoobidiver@netcourrier.com","id":386758}],"summary":"Crash with <svg:use> removed during its own scrollbar attribute mutation event","cf_user_story":"","platform":"All","cf_tracking_firefox38":"---","cf_tracking_e10s":"---","version":"17 Branch","cf_blocking_fx":"---","mentors_detail":[],"cf_feature_b2g":"---","cf_tracking_firefox39":"---","is_creator_accessible":true,"is_confirmed":true,"priority":"--","cf_tracking_firefox17":"+","cf_tracking_firefox37":"---","cf_status_firefox39":"---","assigned_to_detail":{"email":"bugs@pettay.fi","real_name":"Olli Pettay [:smaug]","name":"bugs@pettay.fi","id":39966},"creator":"jruderman@gmail.com","cf_blocking_b2g":"---","last_change_time":"2014-01-10T18:41:15Z","cf_tracking_firefox_esr31":"---","cf_status_b2g_2_2":"---","creator_detail":{"email":"jruderman@gmail.com","real_name":"Jesse Ruderman","name":"jruderman@gmail.com","id":11608},"cf_status_esr10":"fixed","cc":["21@vingtetun.org","abillings@mozilla.com","akeybl@mozilla.com","anthony.s.hughes@gmail.com","bugs@pettay.fi","bzbarsky@mit.edu","kairo@kairo.at","mark@wolfbeast.com","mats@mozilla.com","roc@ocallahan.org","scoobidiver@netcourrier.com"],"assigned_to":"bugs@pettay.fi","groups":[],"see_also":[],"id":793848,"whiteboard":"[adv-track-main17+][adv-track-esr17+] The current testcase is only useful on recent versions","creation_time":"2012-09-24T21:38:26Z","depends_on":[],"cf_tracking_firefox_esr38":"---","cf_status_firefox_esr38":"---","cf_status_b2g_2_1":"---","mentors":[],"dupe_of":null,"resolution":"FIXED","cf_tracking_firefox19":"+","classification":"Components","alias":null,"op_sys":"All","cf_blocking_fennec":"---","status":"RESOLVED","cf_status_b2g_2_0":"---","cf_status_firefox19":"fixed","cf_status_b2g_2_0m":"---","cf_crash_signature":"[@ mozilla::ScrollbarActivity::ActivityOccurred]\r\n[@ mozilla::ScrollbarActivity::CancelActivityFinishedTimer()]\r\n[@ nsListScrollSmoother::Stop()]","cf_status_firefox18":"fixed","is_open":false,"severity":"critical","cf_status_firefox40":"---","cf_tracking_relnote_b2g":"---","cf_tracking_firefox18":"+","flags":[{"modification_date":"2013-05-13T14:32:57Z","creation_date":"2012-10-21T07:29:41Z","type_id":37,"status":"+","name":"in-testsuite","id":561589,"setter":"mats@mozilla.com"}],"cf_status_b2g_1_4":"---","cf_status_firefox37":"---","cf_status_b2g_3_0":"---","component":"Layout","target_milestone":"---","product":"Core","cf_tracking_firefox40":"---"}],"faults":[]}